{"type": "FeatureCollection", "features": [{"type": "Feature", "geometry": {"type": "Point", "coordinates": [70.87999191700067, 32.23903626100002]}, "properties": {"OID_": 0, "Name": "Tube Well - NonFunctional", "Tehsil": "Paharpur", "District": "D.I Khan", "NC": "Paniala 1", "Feature": "Tube Well - Non-Functional"}}, {"type": "Feature", "geometry": {"type": "Point", "coordinates": [70.88854233300069, 32.24422506100006]}, "properties": {"OID_": 0, "Name": "Tube Well 1 -  NonFunctional", "Tehsil": "Paharpur", "District": "D.I Khan", "NC": "Paniala 2", "Feature": "Tube Well - Non-Functional"}}, {"type": "Feature", "geometry": {"type": "Point", "coordinates": [70.8888597340007, 32.24412456100003]}, "properties": {"OID_": 0, "Name": "Tube Well 2 - NonFunctional", "Tehsil": "Paharpur", "District": "D.I Khan", "NC": "Paniala 2", "Feature": "Tube Well - Non-Functional"}}, {"type": "Feature", "geometry": {"type": "Point", "coordinates": [70.88873413200074, 32.24411547200002]}, "properties": {"OID_": 0, "Name": "Water Tank", "Tehsil": "Paharpur", "District": "D.I Khan", "NC": "Paniala 2", "Feature": "Over Head Reservior"}}, {"type": "Feature", "geometry": {"type": "Point", "coordinates": [70.8913888890007, 32.24666666700005]}, "properties": {"OID_": 0, "Name": "Tube Well - NonFunctional", "Tehsil": "Paharpur", "District": "D.I Khan", "NC": "Paniala 2", "Feature": "Tube Well - Non-Functional"}}, {"type": "Feature", "geometry": {"type": "Point", "coordinates": [70.8922222220007, 32.24472222200005]}, "properties": {"OID_": 0, "Name": "Tube Well - NonFunctional", "Tehsil": "Paharpur", "District": "D.I Khan", "NC": "Paniala 2", "Feature": "Tube Well - Non-Functional"}}, {"type": "Feature", "geometry": {"type": "Point", "coordinates": [70.88048000016798, 32.23562599982346]}, "properties": {"OID_": 0, "Name": "Tube Well - Functional", "Tehsil": "Paharpur", "District": "D.I Khan", "NC": "Paniala 2", "Feature": "Tube Well - Functional"}}]}